gauchian/__init__.py
gauchian/__main__.py
gauchian/gauchian.py
gauchian/caller/__init__.py
gauchian/caller/gba_caller.py
gauchian/caller/phasing_gba.py
gauchian/data/GBA_SNP_19.txt
gauchian/data/GBA_SNP_37.txt
gauchian/data/GBA_SNP_38.txt
gauchian/data/GBA_gmm.txt
gauchian/data/GBA_haplotype_19.txt
gauchian/data/GBA_haplotype_37.txt
gauchian/data/GBA_haplotype_38.txt
gauchian/data/GBA_region_19.bed
gauchian/data/GBA_region_37.bed
gauchian/data/GBA_region_38.bed
gauchian/data/GBA_target_variant_19.txt
gauchian/data/GBA_target_variant_37.txt
gauchian/data/GBA_target_variant_38.txt
gauchian/data/GBA_target_variant_homology_region_19.txt
gauchian/data/GBA_target_variant_homology_region_37.txt
gauchian/data/GBA_target_variant_homology_region_38.txt
gauchian/depth_calling/__init__.py
gauchian/depth_calling/bin_count.py
gauchian/depth_calling/copy_number_call.py
gauchian/depth_calling/gene_caller.py
gauchian/depth_calling/gmm.py
gauchian/depth_calling/haplotype.py
gauchian/depth_calling/phasing.py
gauchian/depth_calling/snp_count.py
gauchian/depth_calling/utilities.py
gauchian-1.0.2.dist-info/METADATA
gauchian-1.0.2.dist-info/RECORD
gauchian-1.0.2.dist-info/WHEEL
gauchian-1.0.2.dist-info/entry_points.txt
gauchian-1.0.2.dist-info/top_level.txt
