Metadata-Version: 2.1
Name: gauchian
Version: 1.0.2
Summary: WGS-based GBA variant caller
Home-page: https://github.com/illumina/Gauchian
Author: Xiao Chen
Author-email: xchen2@illumina.com
License: GPLv3
Keywords: GBA
Platform: UNKNOWN
Requires-Dist: pysam
Requires-Dist: numpy
Requires-Dist: scipy
Requires-Dist: statsmodels
